odoo/addons/sequence_python/README.rst
odoo/addons/sequence_python/__init__.py
odoo/addons/sequence_python/__manifest__.py
odoo/addons/sequence_python/i18n/ca.po
odoo/addons/sequence_python/i18n/es.po
odoo/addons/sequence_python/i18n/es_AR.po
odoo/addons/sequence_python/i18n/it.po
odoo/addons/sequence_python/i18n/sequence_python.pot
odoo/addons/sequence_python/models/__init__.py
odoo/addons/sequence_python/models/ir_sequence.py
odoo/addons/sequence_python/readme/CONTRIBUTORS.rst
odoo/addons/sequence_python/readme/DESCRIPTION.rst
odoo/addons/sequence_python/readme/USAGE.rst
odoo/addons/sequence_python/static/description/icon.png
odoo/addons/sequence_python/static/description/index.html
odoo/addons/sequence_python/tests/__init__.py
odoo/addons/sequence_python/tests/test_ir_sequence.py
odoo/addons/sequence_python/views/ir_sequence.xml
odoo14_addon_sequence_python-14.0.1.0.1.dev11.dist-info/METADATA
odoo14_addon_sequence_python-14.0.1.0.1.dev11.dist-info/WHEEL
odoo14_addon_sequence_python-14.0.1.0.1.dev11.dist-info/top_level.txt
odoo14_addon_sequence_python-14.0.1.0.1.dev11.dist-info/RECORD
